lighthouseweb3/__init__.py
lighthouseweb3/functions/__init__.py
lighthouseweb3/functions/axios.py
lighthouseweb3/functions/config.py
lighthouseweb3/functions/create_wallet.py
lighthouseweb3/functions/deal_status.py
lighthouseweb3/functions/download.py
lighthouseweb3/functions/get_api_key.py
lighthouseweb3/functions/get_balance.py
lighthouseweb3/functions/get_file_info.py
lighthouseweb3/functions/get_ipns_record.py
lighthouseweb3/functions/get_uploads.py
lighthouseweb3/functions/ipns_generate_key.py
lighthouseweb3/functions/ipns_publish_record.py
lighthouseweb3/functions/remove_ipns_record.py
lighthouseweb3/functions/upload.py
lighthouseweb3/functions/utils.py
lighthouseweb3-0.1.6.dist-info/licenses/LICENSE.md
lighthouseweb3-0.1.6.dist-info/METADATA
lighthouseweb3-0.1.6.dist-info/WHEEL
lighthouseweb3-0.1.6.dist-info/top_level.txt
lighthouseweb3-0.1.6.dist-info/RECORD
