Metadata-Version: 2.4
Name: lighthouseweb3
Version: 0.1.6
Summary: Lighthouse Python SDK
Home-page: https://github.com/lighthouse-web3/lighthouse-python-sdk
Author: Ravish Sharma | Ayobami Oki | Nandit Mehra
Author-email: Ravish Sharma | Ayobami Oki | Nandit Mehra <ravish@lighthouse.storage>
Maintainer-email: Ravish Sharma | Ayobami Oki | Nandit Mehra <ravish@lighthouse.storage>
License: GPL-3.0
Project-URL: Homepage, https://github.com/lighthouse-web3/lighthouse-python-sdk
Project-URL: Repository, https://github.com/lighthouse-web3/lighthouse-python-sdk
Project-URL: Issues, https://github.com/lighthouse-web3/lighthouse-python-sdk/issues
Keywords: lighthouse,storage,sdk,python,filecoin,ipfs,web3,perpetual
Classifier: Operating System :: OS Independent
Classifier: Intended Audience :: Developers
Classifier: Topic :: Software Development :: Build Tools
Classifier: Programming Language :: Python :: 3.6
Classifier: Programming Language :: Python :: 3.7
Classifier: Programming Language :: Python :: 3.8
Classifier: Programming Language :: Python :: 3.9
Classifier: Programming Language :: Python :: 3.10
Classifier: Programming Language :: Python :: 3.11
Requires-Python: >=3.6
License-File: LICENSE.md
Requires-Dist: requests>=2.31.0
Requires-Dist: certifi>=2023.5.7
Requires-Dist: charset-normalizer>=3.1.0
Requires-Dist: idna>=3.4
Requires-Dist: urllib3>=2.0.2
Requires-Dist: eth-account>=0.13.7
Dynamic: author
Dynamic: home-page
Dynamic: license-file
Dynamic: requires-python
